Metadata-Version: 1.0
Name: deep-teaching-tools
Version: 0.3
Summary: This Python module is part of the deep.TEACHING project and provides CLI tools to work with Jupyter notebooks and teaching materials.
Home-page: https://gitlab.com/deep.TEACHING/deep-teaching-tools
Author: Christoph Jansen
Author-email: Christoph.Jansen@htw-berlin.de
License: MIT
Platform: any
